chartinglib-0.1.0.dist-info/METADATA
chartinglib-0.1.0.dist-info/WHEEL
chartinglib-0.1.0.dist-info/entry_points.txt
chartinglib-0.1.0.dist-info/licenses/LICENSE
chartinglib/__init__.py
chartinglib/chart_data_processing.py
chartinglib/charting_main.py
chartinglib/charting_widget.py
chartinglib-0.1.0.dist-info/RECORD
