Metadata-Version: 2.1
Name: chartinglib
Version: 0.1.0
Summary: Integrate Plotly charts into Textual TUI applications with a customizable ChartWidget.
Author-Email: Jaimin Patel <pateljaimin1707@email.com>
License: MIT
Project-URL: Homepage, https://github.com/Jaimin-ptl07/ChartingLib
Requires-Python: >=3.11
Requires-Dist: textual>=0.40.0
Requires-Dist: plotly>=5.0.0
Requires-Dist: pandas
